json_cli_tool-1.0.4.dist-info/licenses/LICENSE
json_validator_cli/__init__.py
json_validator_cli/cli.py
json_validator_cli/core.py
json_validator_cli/__pycache__/__init__.cpython-311.pyc
json_validator_cli/__pycache__/cli.cpython-311.pyc
json_validator_cli/__pycache__/core.cpython-311.pyc
json_cli_tool-1.0.4.dist-info/METADATA
json_cli_tool-1.0.4.dist-info/WHEEL
json_cli_tool-1.0.4.dist-info/entry_points.txt
json_cli_tool-1.0.4.dist-info/top_level.txt
json_cli_tool-1.0.4.dist-info/RECORD
