Metadata-Version: 2.4
Name: json-cli-tool
Version: 1.0.4
Summary: A CLI tool to beautify, validate, and minify JSON data.
Home-page: https://github.com/qazi112/json-validator
Author: Qazi Arsalan Shah
Project-URL: Source, https://github.com/qazi112/json-validator
Project-URL: Tracker, https://github.com/qazi112/json-validator/issues
Classifier: Programming Language :: Python :: 3
Classifier: License :: OSI Approved :: MIT License
Classifier: Operating System :: OS Independent
Requires-Python: >=3.7
License-File: LICENSE
Requires-Dist: pyperclip>=1.8
Requires-Dist: rich>=13.0
Dynamic: author
Dynamic: classifier
Dynamic: description-content-type
Dynamic: home-page
Dynamic: license-file
Dynamic: project-url
Dynamic: requires-dist
Dynamic: requires-python
Dynamic: summary
